dict_of_lists/__init__.py
dict_of_lists/dict_of_lists.py
dict_of_lists-1.0.0.dist-info/METADATA
dict_of_lists-1.0.0.dist-info/WHEEL
dict_of_lists-1.0.0.dist-info/top_level.txt
dict_of_lists-1.0.0.dist-info/RECORD
