Metadata-Version: 2.1
Name: dict-of-lists
Version: 1.0.0
Summary: A dictionary with empty list/sets pre-setted values
Home-page: https://github.com/ehsankarbasian/dict_of_lists
Author: Ehsan Karbasian
Author-email: ehsan.karbasian@gmail.com
Classifier: Programming Language :: Python :: 3
Classifier: License :: OSI Approved :: MIT License
Classifier: Operating System :: OS Independent
Requires-Python: >=3.6
